error_dispatcher_client/__init__.py
error_dispatcher_client/base_metrics.py
error_dispatcher_client/fastapi_metrics.py
error_dispatcher_client/flask_metrics.py
error_dispatcher_client/providers/__init__.py
error_dispatcher_client/providers/base_provider.py
error_dispatcher_client/providers/discord_provider.py
error_dispatcher_client/providers/email_provider.py
error_dispatcher_client/providers/kafka_provider.py
error_dispatcher_client/templates/__init__.py
error_dispatcher_client/templates/base_template.py
error_dispatcher_client-1.0.8.dist-info/licenses/LICENSE
tests/__init__.py
tests/test_email.py
tests/test_fastapi.py
tests/test_flask.py
tests/test_kafka.py
error_dispatcher_client-1.0.8.dist-info/METADATA
error_dispatcher_client-1.0.8.dist-info/WHEEL
error_dispatcher_client-1.0.8.dist-info/top_level.txt
error_dispatcher_client-1.0.8.dist-info/RECORD
