Metadata-Version: 2.4
Name: error_dispatcher_client
Version: 1.0.8
Summary: A Python package for tracking and handling errors with support for multiple providers like Kafka and Email.
Home-page: https://github.com/solinftec/error_dispatcher_client
Author: Willian Antunes
Author-email: Willian Antunes <willian.antunes@solinftec.com>
License: MIT License
Project-URL: Documentation, https://github.com/solinftec/error_dispatcher_client#readme
Project-URL: Repository, https://github.com/solinftec/error_dispatcher_client
Keywords: error handling,kafka,email,tracking
Classifier: Programming Language :: Python :: 3
Classifier: License :: OSI Approved :: MIT License
Classifier: Operating System :: OS Independent
Requires-Python: >=3.7
License-File: LICENSE
Requires-Dist: flask
Requires-Dist: fastapi>=0.108.0
Requires-Dist: confluent-kafka
Requires-Dist: discord-webhook
Dynamic: author
Dynamic: home-page
Dynamic: license-file
Dynamic: requires-python
